{"lastUsed":1627206449619,"path":"D:\/works\/eclipse-workspace\/esp32_project\/esp32_car","projectCount":1,"recentFiles":[{"path":"\/esp32_car","parentWorkspace":"D:\/works\/eclipse-workspace\/esp32_project\/esp32_car","name":"sdkconfig","lastModified":1627186576142,"locationURI":"file:\/D:\/works\/eclipse-workspace\/esp32_project\/esp32_car\/esp32_car\/sdkconfig"},{"path":"\/esp32_car\/main","parentWorkspace":"D:\/works\/eclipse-workspace\/esp32_project\/esp32_car","name":"tcp_client.c","lastModified":1627206240620,"locationURI":"file:\/D:\/works\/eclipse-workspace\/esp32_project\/esp32_car\/esp32_car\/main\/tcp_client.c"}]}